ml_instrumentation/Collector.py
ml_instrumentation/Sampler.py
ml_instrumentation/Writer.py
ml_instrumentation/__init__.py
ml_instrumentation/metadata.py
ml_instrumentation/reader.py
ml_instrumentation/utils.py
ml_instrumentation/_utils/__init__.py
ml_instrumentation/_utils/sqlite.py
ml_instrumentation/backends/__init__.py
ml_instrumentation/backends/base.py
ml_instrumentation/backends/sqlite.py
ml_instrumentation/backends/tsdb.py
ml_instrument-0.5.0.dist-info/METADATA
ml_instrument-0.5.0.dist-info/WHEEL
ml_instrument-0.5.0.dist-info/licenses/LICENSE
ml_instrument-0.5.0.dist-info/RECORD
