Metadata-Version: 2.4
Name: ml-instrument
Version: 0.5.0
Author-email: Andy Patterson <andnpatterson@gmail.com>
License: MIT
License-File: LICENSE
Classifier: Programming Language :: Python :: Implementation :: CPython
Classifier: Programming Language :: Python :: Implementation :: PyPy
Requires-Python: <3.14,>=3.10
Requires-Dist: connectorx~=0.4
Requires-Dist: filelock~=3.13
Requires-Dist: numpy<=2.2.4,>=1.26
Requires-Dist: polars~=1.23
Requires-Dist: pyarrow~=19.0
Requires-Dist: sqlalchemy-utils>=0.41.2
Requires-Dist: sqlalchemy>=2.0.40
